[
    {
        "title": "RevenueCat Shipaton 2025",
        "date": "Jul 31 - Oct 01, 2025",
        "link": "https://revenuecat-shipaton-2025.devpost.com/?ref_feature=challenge&ref_medium=discover"
    },
    {
        "title": "GKE Turns 10 Hackathon",
        "date": "Aug 18 - Sep 22, 2025",
        "link": "https://gketurns10.devpost.com/?ref_feature=challenge&ref_medium=discover"
    },
    {
        "title": "Tableau Next Virtual Hackathon",
        "date": "Jul 24 - Sep 22, 2025",
        "link": "https://tableau.devpost.com/?ref_feature=challenge&ref_medium=discover"
    },
    {
        "title": "Google Chrome Built-in AI Challenge 2025",
        "date": "Sep 09 - Nov 01, 2025",
        "link": "https://googlechromeai2025.devpost.com/?ref_feature=challenge&ref_medium=discover"
    },
    {
        "title": "AWS AI Agent Global Hackathon",
        "date": "Sep 08 - Oct 20, 2025",
        "link": "https://aws-agent-hackathon.devpost.com/?ref_feature=challenge&ref_medium=discover"
    },
    {
        "title": "Fun and Games with Devvit Web",
        "date": "Aug 28 - Sep 19, 2025",
        "link": "https://redditfunandgames.devpost.com/?ref_feature=challenge&ref_medium=discover"
    },
    {
        "title": "Proof of Concept",
        "date": "Jul 24 - Sep 19, 2025",
        "link": "https://proofofconcept.devpost.com/?ref_feature=challenge&ref_medium=discover"
    },
    {
        "title": "Chroma Awards: AI Film, Music Videos, and Games",
        "date": "Aug 31 - Nov 04, 2025",
        "link": "https://chromaawards.devpost.com/?ref_feature=challenge&ref_medium=discover"
    },
    {
        "title": "Baseline Tooling Hackathon",
        "date": "Sep 02 - Oct 06, 2025",
        "link": "https://baseline.devpost.com/?ref_feature=challenge&ref_medium=discover"
    }
]